{
  "type": "FeatureCollection",
  "features": [
    {
      "type": "Feature",
      "id": "node/483270470",
      "properties": {
        "timestamp": "2009-09-04T15:53:35Z",
        "version": 1,
        "changeset": 2370695,
        "historic": "monument",
        "name": "Portal da Xuxa",
        "id": "node/483270470"
      },
      "geometry": {
        "type": "Point",
        "coordinates": [
          -54.4806983,
          -27.8699442
        ]
      }
    }
  ]
}
