{
  "type": "FeatureCollection",
  "features": [
    {
      "type": "Feature",
      "id": "node/530312171",
      "properties": {
        "timestamp": "2009-10-14T03:14:34Z",
        "version": 1,
        "changeset": 2841609,
        "amenity": "school",
        "name": "Instituto Estadual de Educação Madre Tereza",
        "id": "node/530312171"
      },
      "geometry": {
        "type": "Point",
        "coordinates": [
          -53.4029214,
          -27.4784301
        ]
      }
    }
  ]
}
