{
  "type": "FeatureCollection",
  "features": [
    {
      "type": "Feature",
      "id": "node/536732189",
      "properties": {
        "timestamp": "2009-10-20T22:14:53Z",
        "version": 2,
        "changeset": 2907504,
        "amenity": "hospital",
        "name": "Hospital Centenário",
        "id": "node/536732189"
      },
      "geometry": {
        "type": "Point",
        "coordinates": [
          -51.1485433,
          -29.7764076
        ]
      }
    }
  ]
}
