{
  "type": "FeatureCollection",
  "features": [
    {
      "type": "Feature",
      "id": "node/439239039",
      "properties": {
        "timestamp": "2009-07-10T13:25:51Z",
        "version": 1,
        "changeset": 1788419,
        "amenity": "hospital",
        "name": "Hospital Tacchini",
        "id": "node/439239039"
      },
      "geometry": {
        "type": "Point",
        "coordinates": [
          -51.5149721,
          -29.1674783
        ]
      }
    },
    {
      "type": "Feature",
      "id": "node/506711892",
      "properties": {
        "timestamp": "2009-09-24T17:33:49Z",
        "version": 1,
        "changeset": 2606964,
        "amenity": "hospital",
        "name": "Posto Unimed",
        "id": "node/506711892"
      },
      "geometry": {
        "type": "Point",
        "coordinates": [
          -51.5114926,
          -29.1638877
        ]
      }
    },
    {
      "type": "Feature",
      "id": "node/506712047",
      "properties": {
        "timestamp": "2009-09-24T17:34:11Z",
        "version": 1,
        "changeset": 2606964,
        "amenity": "hospital",
        "name": "Posto de Saúde",
        "id": "node/506712047"
      },
      "geometry": {
        "type": "Point",
        "coordinates": [
          -51.5145567,
          -29.1799782
        ]
      }
    }
  ]
}
