{
  "type": "FeatureCollection",
  "features": [
    {
      "type": "Feature",
      "id": "node/380021819",
      "properties": {
        "timestamp": "2009-04-22T00:19:55Z",
        "version": 1,
        "changeset": 890400,
        "amenity": "clinic",
        "name": "Unidade de Saúde Ana Neves",
        "id": "node/380021819"
      },
      "geometry": {
        "type": "Point",
        "coordinates": [
          -48.3138462,
          -25.5706457
        ]
      }
    }
  ]
}
