{
  "type": "FeatureCollection",
  "features": [
    {
      "type": "Feature",
      "id": "node/435264985",
      "properties": {
        "timestamp": "2009-07-07T02:02:25Z",
        "version": 2,
        "changeset": 1758216,
        "amenity": "pharmacy",
        "operator": "Droga Raia",
        "id": "node/435264985"
      },
      "geometry": {
        "type": "Point",
        "coordinates": [
          -46.8492533,
          -23.4948185
        ]
      }
    },
    {
      "type": "Feature",
      "id": "node/435905680",
      "properties": {
        "timestamp": "2009-07-07T02:02:26Z",
        "version": 1,
        "changeset": 1758216,
        "amenity": "pharmacy",
        "name": "Farma Life",
        "id": "node/435905680"
      },
      "geometry": {
        "type": "Point",
        "coordinates": [
          -46.8492619,
          -23.4934489
        ]
      }
    },
    {
      "type": "Feature",
      "id": "node/435905692",
      "properties": {
        "timestamp": "2009-07-07T02:02:26Z",
        "version": 1,
        "changeset": 1758216,
        "amenity": "pharmacy",
        "name": "Droga Rani",
        "id": "node/435905692"
      },
      "geometry": {
        "type": "Point",
        "coordinates": [
          -46.8489958,
          -23.4956214
        ]
      }
    }
  ]
}
