{
  "type": "FeatureCollection",
  "features": [
    {
      "type": "Feature",
      "id": "node/445445602",
      "properties": {
        "timestamp": "2009-09-21T09:12:11Z",
        "version": 2,
        "changeset": 2554880,
        "amenity": "school",
        "name": "Cel Lep",
        "id": "node/445445602"
      },
      "geometry": {
        "type": "Point",
        "coordinates": [
          -46.8550169,
          -23.4847006
        ]
      }
    }
  ]
}
