{
  "type": "FeatureCollection",
  "features": [
    {
      "type": "Feature",
      "id": "node/415419665",
      "properties": {
        "timestamp": "2009-06-03T19:51:18Z",
        "version": 1,
        "changeset": 1415727,
        "name": "Urubici Park Hotel",
        "tourism": "hotel",
        "id": "node/415419665"
      },
      "geometry": {
        "type": "Point",
        "coordinates": [
          -49.5844142,
          -27.9946144
        ]
      }
    }
  ]
}
