{
  "type": "FeatureCollection",
  "features": [
    {
      "type": "Feature",
      "id": "node/482734199",
      "properties": {
        "timestamp": "2009-09-04T20:42:57Z",
        "version": 2,
        "changeset": 2373736,
        "name": "Piramide",
        "tourism": "hotel",
        "id": "node/482734199"
      },
      "geometry": {
        "type": "Point",
        "coordinates": [
          -48.1088989,
          -24.5232485
        ]
      }
    }
  ]
}
