{
  "type": "FeatureCollection",
  "features": [
    {
      "type": "Feature",
      "id": "node/564370436",
      "properties": {
        "timestamp": "2009-11-15T00:13:20Z",
        "version": 1,
        "changeset": 3118336,
        "amenity": "kindergarten",
        "name": "Peixinho Dourado",
        "id": "node/564370436"
      },
      "geometry": {
        "type": "Point",
        "coordinates": [
          -49.2522151,
          -25.4286142
        ]
      }
    }
  ]
}
