{
  "type": "FeatureCollection",
  "features": [
    {
      "type": "Feature",
      "id": "node/324498064",
      "properties": {
        "timestamp": "2009-01-02T01:24:48Z",
        "version": 1,
        "changeset": 706983,
        "amenity": "library",
        "created_by": "Merkaartor 0.12",
        "name": "Biblioteca Pública",
        "id": "node/324498064"
      },
      "geometry": {
        "type": "Point",
        "coordinates": [
          -43.9390307,
          -19.9314109
        ]
      }
    },
    {
      "type": "Feature",
      "id": "node/324498101",
      "properties": {
        "timestamp": "2009-09-22T18:54:44Z",
        "version": 3,
        "changeset": 2574434,
        "amenity": "library",
        "name": "Biblioteca Pública de Minas Gerais",
        "id": "node/324498101"
      },
      "geometry": {
        "type": "Point",
        "coordinates": [
          -43.9391943,
          -19.9329666
        ]
      }
    }
  ]
}
