{
  "type": "FeatureCollection",
  "features": [
    {
      "type": "Feature",
      "id": "node/583066544",
      "properties": {
        "timestamp": "2009-12-08T01:16:24Z",
        "version": 1,
        "changeset": 3321422,
        "amenity": "library",
        "name": "Biblioteca municipal",
        "id": "node/583066544"
      },
      "geometry": {
        "type": "Point",
        "coordinates": [
          -47.4707061,
          -21.7082537
        ]
      }
    }
  ]
}
