{
  "type": "FeatureCollection",
  "features": [
    {
      "type": "Feature",
      "id": "node/322253881",
      "properties": {
        "timestamp": "2008-12-28T14:33:26Z",
        "version": 2,
        "changeset": 644153,
        "amenity": "school",
        "name": "Escola Estadual Dona Francisca Josina",
        "id": "node/322253881"
      },
      "geometry": {
        "type": "Point",
        "coordinates": [
          -43.6150651,
          -19.3296297
        ]
      }
    }
  ]
}
